{
  "id": "1762902163560000600",
  "adapter": "city",
  "dimension": "2D",
  "theme": "city",
  "aesthetic": "dark",
  "rooms": [
    {
      "index": 1,
      "type": "loot",
      "desc": "A fuel cell gleams faintly."
    },
    {
      "index": 2,
      "type": "trap",
      "desc": "A collapsing floor lies ahead."
    },
    {
      "index": 3,
      "type": "combat",
      "desc": "A guard lurks nearby."
    },
    {
      "index": 4,
      "type": "trap",
      "desc": "A laser grid lies ahead."
    },
    {
      "index": 5,
      "type": "rest",
      "desc": "A quiet alcove offers respite."
    },
    {
      "index": 6,
      "type": "loot",
      "desc": "A fuel cell gleams faintly."
    },
    {
      "index": 7,
      "type": "rest",
      "desc": "A quiet alcove offers respite."
    },
    {
      "index": 8,
      "type": "combat",
      "desc": "A bandit lurks nearby."
    },
    {
      "index": 9,
      "type": "combat",
      "desc": "A guard lurks nearby."
    },
    {
      "index": 10,
      "type": "loot",
      "desc": "A ancient chest gleams faintly."
    }
  ],
  "seed": 1762902163560000600,
  "current": 0,
  "game_state": "exploring",
  "party": null,
  "log": [
    "World spawned: city (seed=1762902163560000600)"
  ],
  "prompts": []
}